examples/data/color/color0000.jpg
examples/data/color/color0001.jpg
examples/data/color/color0002.jpg
examples/data/color/color0003.jpg
examples/data/color/color0004.jpg
examples/data/color/color0005.jpg
examples/data/color/color0006.jpg
examples/data/color/color0007.jpg
examples/data/color/color0008.jpg
examples/data/color/color0009.jpg
examples/data/color/color0010.jpg
examples/data/color/color0011.jpg
examples/data/color/color0012.jpg
examples/data/color/color0013.jpg
examples/data/color/color0014.jpg
examples/data/color/color0015.jpg
examples/data/color/color0016.jpg
examples/data/color/color0017.jpg
examples/data/color/color0018.jpg
examples/data/color/color0019.jpg
examples/data/color/color0020.jpg
examples/data/color/color0021.jpg
examples/data/color/color0022.jpg
examples/data/color/color0023.jpg
examples/data/color/color0024.jpg
examples/data/color/color0025.jpg
examples/data/color/color0026.jpg
examples/data/color/color0027.jpg
examples/data/color/color0028.jpg
examples/data/color/color0029.jpg
examples/data/color/color0030.jpg
examples/data/color/color0031.jpg
examples/data/color/color0032.jpg
examples/data/color/color0033.jpg
examples/data/color/color0034.jpg
examples/data/color/color0035.jpg
examples/data/color/color0036.jpg
examples/data/color/color0037.jpg
examples/data/color/color0038.jpg
examples/data/color/color0039.jpg
examples/data/color/color0040.jpg
examples/data/color/color0041.jpg
examples/data/color/color0042.jpg
examples/data/color/color0043.jpg
examples/data/color/color0044.jpg
examples/data/color/color0045.jpg
examples/data/color/color0046.jpg
examples/data/color/color0047.jpg
examples/data/color/color0048.jpg
examples/data/color/color0049.jpg
examples/data/color/color0050.jpg
examples/data/color/color0051.jpg
examples/data/color/color0052.jpg
examples/data/color/color0053.jpg
examples/data/color/color0054.jpg
examples/data/color/color0055.jpg
examples/data/color/color0056.jpg
examples/data/color/color0057.jpg
imgseries-0.13.2.dist-info/licenses/LICENSE
imgseries-0.13.2.dist-info/METADATA
imgseries-0.13.2.dist-info/WHEEL
imgseries-0.13.2.dist-info/top_level.txt
imgseries-0.13.2.dist-info/RECORD
