Metadata-Version: 2.4
Name: imgseries
Version: 0.13.2
Summary: Image inspection and analysis tools for image series.
Author-email: Olivier Vincent <ovinc.py@gmail.com>
License: CeCILL-2.1
Project-URL: Homepage, https://github.com/ovinc/imgseries
Project-URL: Documentation, https://github.com/ovinc/imgseries/README.md
Project-URL: Repository, https://github.com/ovinc/imgseries.git
Keywords: image,analysis,inspection,series,contour,tracking,grey,level,gray,stack,video
Classifier: Programming Language :: Python :: 3
Classifier: Operating System :: OS Independent
Classifier: License :: OSI Approved :: CEA CNRS Inria Logiciel Libre License, version 2.1 (CeCILL-2.1)
Requires-Python: >=3.6
License-File: LICENSE
Requires-Dist: scikit-image
Requires-Dist: matplotlib
Requires-Dist: numpy
Requires-Dist: importlib-metadata
Requires-Dist: tqdm
Requires-Dist: filo>=2.2.1
Requires-Dist: imgbasics>=0.4.1
Requires-Dist: drapo>=1.2.1
Requires-Dist: h5py
Provides-Extra: avi
Requires-Dist: pims; extra == "avi"
Requires-Dist: av; extra == "avi"
Provides-Extra: git
Requires-Dist: gittools>=0.7; extra == "git"
Dynamic: license-file
